{
  "last_updated": "2026-04-29T23:53:22.011632",
  "symbols": {
    "BTCUSDT": {
      "price": 75892.82,
      "strategies": [
        {
          "name": "contrarian_watch_overheated",
          "status": "Watch",
          "score": 0.5,
          "conditions_passed": 1,
          "total_conditions": 1
        },
        {
          "name": "ma_cross_trend",
          "status": "Idle",
          "score": 0.0,
          "conditions_passed": 0,
          "total_conditions": 0
        },
        {
          "name": "ma_cross_trend_short",
          "status": "Idle",
          "score": 0.0,
          "conditions_passed": 0,
          "total_conditions": 0
        },
        {
          "name": "contrarian_watch_oversold",
          "status": "Idle",
          "score": 0.0,
          "conditions_passed": 0,
          "total_conditions": 0
        },
        {
          "name": "hilbert_cycle",
          "status": "Idle",
          "score": 0.0,
          "conditions_passed": 0,
          "total_conditions": 0
        },
        {
          "name": "stochastic_breakout",
          "status": "Idle",
          "score": 0.0,
          "conditions_passed": 0,
          "total_conditions": 0
        },
        {
          "name": "rsi_trend",
          "status": "Idle",
          "score": 0.0,
          "conditions_passed": 0,
          "total_conditions": 0
        },
        {
          "name": "bb_mean_reversion",
          "status": "Idle",
          "score": 0.0,
          "conditions_passed": 0,
          "total_conditions": 0
        },
        {
          "name": "ema_cross_fast",
          "status": "Idle",
          "score": 0.0,
          "conditions_passed": 0,
          "total_conditions": 0
        },
        {
          "name": "rsi_mid_bounce",
          "status": "Idle",
          "score": 0.0,
          "conditions_passed": 0,
          "total_conditions": 0
        },
        {
          "name": "volume_spike",
          "status": "Idle",
          "score": 0.0,
          "conditions_passed": 0,
          "total_conditions": 0
        },
        {
          "name": "price_channel_break",
          "status": "Idle",
          "score": 0.0,
          "conditions_passed": 0,
          "total_conditions": 0
        },
        {
          "name": "momentum_divergence",
          "status": "Idle",
          "score": 0.0,
          "conditions_passed": 0,
          "total_conditions": 0
        }
      ]
    },
    "ETHUSDT": {
      "price": 2270.81,
      "strategies": [
        {
          "name": "ma_cross_trend",
          "status": "Idle",
          "score": 0.0,
          "conditions_passed": 0,
          "total_conditions": 0
        },
        {
          "name": "ma_cross_trend_short",
          "status": "Idle",
          "score": 0.0,
          "conditions_passed": 0,
          "total_conditions": 0
        },
        {
          "name": "contrarian_watch_overheated",
          "status": "Idle",
          "score": 0.0,
          "conditions_passed": 0,
          "total_conditions": 0
        },
        {
          "name": "contrarian_watch_oversold",
          "status": "Idle",
          "score": 0.0,
          "conditions_passed": 0,
          "total_conditions": 0
        },
        {
          "name": "hilbert_cycle",
          "status": "Idle",
          "score": 0.0,
          "conditions_passed": 0,
          "total_conditions": 0
        },
        {
          "name": "stochastic_breakout",
          "status": "Idle",
          "score": 0.0,
          "conditions_passed": 0,
          "total_conditions": 0
        },
        {
          "name": "rsi_trend",
          "status": "Idle",
          "score": 0.0,
          "conditions_passed": 0,
          "total_conditions": 0
        },
        {
          "name": "bb_mean_reversion",
          "status": "Idle",
          "score": 0.0,
          "conditions_passed": 0,
          "total_conditions": 0
        },
        {
          "name": "ema_cross_fast",
          "status": "Idle",
          "score": 0.0,
          "conditions_passed": 0,
          "total_conditions": 0
        },
        {
          "name": "rsi_mid_bounce",
          "status": "Idle",
          "score": 0.0,
          "conditions_passed": 0,
          "total_conditions": 0
        },
        {
          "name": "volume_spike",
          "status": "Idle",
          "score": 0.0,
          "conditions_passed": 0,
          "total_conditions": 0
        },
        {
          "name": "price_channel_break",
          "status": "Idle",
          "score": 0.0,
          "conditions_passed": 0,
          "total_conditions": 0
        },
        {
          "name": "momentum_divergence",
          "status": "Idle",
          "score": 0.0,
          "conditions_passed": 0,
          "total_conditions": 0
        }
      ]
    },
    "BNBUSDT": {
      "price": 616.63,
      "strategies": [
        {
          "name": "ma_cross_trend",
          "status": "Idle",
          "score": 0.0,
          "conditions_passed": 0,
          "total_conditions": 0
        },
        {
          "name": "ma_cross_trend_short",
          "status": "Idle",
          "score": 0.0,
          "conditions_passed": 0,
          "total_conditions": 0
        },
        {
          "name": "contrarian_watch_overheated",
          "status": "Idle",
          "score": 0.0,
          "conditions_passed": 0,
          "total_conditions": 0
        },
        {
          "name": "contrarian_watch_oversold",
          "status": "Idle",
          "score": 0.0,
          "conditions_passed": 0,
          "total_conditions": 0
        },
        {
          "name": "hilbert_cycle",
          "status": "Idle",
          "score": 0.0,
          "conditions_passed": 0,
          "total_conditions": 0
        },
        {
          "name": "stochastic_breakout",
          "status": "Idle",
          "score": 0.0,
          "conditions_passed": 0,
          "total_conditions": 0
        },
        {
          "name": "rsi_trend",
          "status": "Idle",
          "score": 0.0,
          "conditions_passed": 0,
          "total_conditions": 0
        },
        {
          "name": "bb_mean_reversion",
          "status": "Idle",
          "score": 0.0,
          "conditions_passed": 0,
          "total_conditions": 0
        },
        {
          "name": "ema_cross_fast",
          "status": "Idle",
          "score": 0.0,
          "conditions_passed": 0,
          "total_conditions": 0
        },
        {
          "name": "rsi_mid_bounce",
          "status": "Idle",
          "score": 0.0,
          "conditions_passed": 0,
          "total_conditions": 0
        },
        {
          "name": "volume_spike",
          "status": "Idle",
          "score": 0.0,
          "conditions_passed": 0,
          "total_conditions": 0
        },
        {
          "name": "price_channel_break",
          "status": "Idle",
          "score": 0.0,
          "conditions_passed": 0,
          "total_conditions": 0
        },
        {
          "name": "momentum_divergence",
          "status": "Idle",
          "score": 0.0,
          "conditions_passed": 0,
          "total_conditions": 0
        }
      ]
    },
    "SOLUSDT": {
      "price": 83.22,
      "strategies": [
        {
          "name": "ma_cross_trend",
          "status": "Idle",
          "score": 0.0,
          "conditions_passed": 0,
          "total_conditions": 0
        },
        {
          "name": "ma_cross_trend_short",
          "status": "Idle",
          "score": 0.0,
          "conditions_passed": 0,
          "total_conditions": 0
        },
        {
          "name": "contrarian_watch_overheated",
          "status": "Idle",
          "score": 0.0,
          "conditions_passed": 0,
          "total_conditions": 0
        },
        {
          "name": "contrarian_watch_oversold",
          "status": "Idle",
          "score": 0.0,
          "conditions_passed": 0,
          "total_conditions": 0
        },
        {
          "name": "hilbert_cycle",
          "status": "Idle",
          "score": 0.0,
          "conditions_passed": 0,
          "total_conditions": 0
        },
        {
          "name": "stochastic_breakout",
          "status": "Idle",
          "score": 0.0,
          "conditions_passed": 0,
          "total_conditions": 0
        },
        {
          "name": "rsi_trend",
          "status": "Idle",
          "score": 0.0,
          "conditions_passed": 0,
          "total_conditions": 0
        },
        {
          "name": "bb_mean_reversion",
          "status": "Idle",
          "score": 0.0,
          "conditions_passed": 0,
          "total_conditions": 0
        },
        {
          "name": "ema_cross_fast",
          "status": "Idle",
          "score": 0.0,
          "conditions_passed": 0,
          "total_conditions": 0
        },
        {
          "name": "rsi_mid_bounce",
          "status": "Idle",
          "score": 0.0,
          "conditions_passed": 0,
          "total_conditions": 0
        },
        {
          "name": "volume_spike",
          "status": "Idle",
          "score": 0.0,
          "conditions_passed": 0,
          "total_conditions": 0
        },
        {
          "name": "price_channel_break",
          "status": "Idle",
          "score": 0.0,
          "conditions_passed": 0,
          "total_conditions": 0
        },
        {
          "name": "momentum_divergence",
          "status": "Idle",
          "score": 0.0,
          "conditions_passed": 0,
          "total_conditions": 0
        }
      ]
    },
    "XRPUSDT": {
      "price": 1.3622,
      "strategies": [
        {
          "name": "ma_cross_trend",
          "status": "Idle",
          "score": 0.0,
          "conditions_passed": 0,
          "total_conditions": 0
        },
        {
          "name": "ma_cross_trend_short",
          "status": "Idle",
          "score": 0.0,
          "conditions_passed": 0,
          "total_conditions": 0
        },
        {
          "name": "contrarian_watch_overheated",
          "status": "Idle",
          "score": 0.0,
          "conditions_passed": 0,
          "total_conditions": 0
        },
        {
          "name": "contrarian_watch_oversold",
          "status": "Idle",
          "score": 0.0,
          "conditions_passed": 0,
          "total_conditions": 0
        },
        {
          "name": "hilbert_cycle",
          "status": "Idle",
          "score": 0.0,
          "conditions_passed": 0,
          "total_conditions": 0
        },
        {
          "name": "stochastic_breakout",
          "status": "Idle",
          "score": 0.0,
          "conditions_passed": 0,
          "total_conditions": 0
        },
        {
          "name": "rsi_trend",
          "status": "Idle",
          "score": 0.0,
          "conditions_passed": 0,
          "total_conditions": 0
        },
        {
          "name": "bb_mean_reversion",
          "status": "Idle",
          "score": 0.0,
          "conditions_passed": 0,
          "total_conditions": 0
        },
        {
          "name": "ema_cross_fast",
          "status": "Idle",
          "score": 0.0,
          "conditions_passed": 0,
          "total_conditions": 0
        },
        {
          "name": "rsi_mid_bounce",
          "status": "Idle",
          "score": 0.0,
          "conditions_passed": 0,
          "total_conditions": 0
        },
        {
          "name": "volume_spike",
          "status": "Idle",
          "score": 0.0,
          "conditions_passed": 0,
          "total_conditions": 0
        },
        {
          "name": "price_channel_break",
          "status": "Idle",
          "score": 0.0,
          "conditions_passed": 0,
          "total_conditions": 0
        },
        {
          "name": "momentum_divergence",
          "status": "Idle",
          "score": 0.0,
          "conditions_passed": 0,
          "total_conditions": 0
        }
      ]
    },
    "ADAUSDT": {
      "price": 0.2441,
      "strategies": [
        {
          "name": "ma_cross_trend",
          "status": "Idle",
          "score": 0.0,
          "conditions_passed": 0,
          "total_conditions": 0
        },
        {
          "name": "ma_cross_trend_short",
          "status": "Idle",
          "score": 0.0,
          "conditions_passed": 0,
          "total_conditions": 0
        },
        {
          "name": "contrarian_watch_overheated",
          "status": "Idle",
          "score": 0.0,
          "conditions_passed": 0,
          "total_conditions": 0
        },
        {
          "name": "contrarian_watch_oversold",
          "status": "Idle",
          "score": 0.0,
          "conditions_passed": 0,
          "total_conditions": 0
        },
        {
          "name": "hilbert_cycle",
          "status": "Idle",
          "score": 0.0,
          "conditions_passed": 0,
          "total_conditions": 0
        },
        {
          "name": "stochastic_breakout",
          "status": "Idle",
          "score": 0.0,
          "conditions_passed": 0,
          "total_conditions": 0
        },
        {
          "name": "rsi_trend",
          "status": "Idle",
          "score": 0.0,
          "conditions_passed": 0,
          "total_conditions": 0
        },
        {
          "name": "bb_mean_reversion",
          "status": "Idle",
          "score": 0.0,
          "conditions_passed": 0,
          "total_conditions": 0
        },
        {
          "name": "ema_cross_fast",
          "status": "Idle",
          "score": 0.0,
          "conditions_passed": 0,
          "total_conditions": 0
        },
        {
          "name": "rsi_mid_bounce",
          "status": "Idle",
          "score": 0.0,
          "conditions_passed": 0,
          "total_conditions": 0
        },
        {
          "name": "volume_spike",
          "status": "Idle",
          "score": 0.0,
          "conditions_passed": 0,
          "total_conditions": 0
        },
        {
          "name": "price_channel_break",
          "status": "Idle",
          "score": 0.0,
          "conditions_passed": 0,
          "total_conditions": 0
        },
        {
          "name": "momentum_divergence",
          "status": "Idle",
          "score": 0.0,
          "conditions_passed": 0,
          "total_conditions": 0
        }
      ]
    },
    "DOGEUSDT": {
      "price": 0.10353,
      "strategies": [
        {
          "name": "ma_cross_trend",
          "status": "Idle",
          "score": 0.0,
          "conditions_passed": 0,
          "total_conditions": 0
        },
        {
          "name": "ma_cross_trend_short",
          "status": "Idle",
          "score": 0.0,
          "conditions_passed": 0,
          "total_conditions": 0
        },
        {
          "name": "contrarian_watch_overheated",
          "status": "Idle",
          "score": 0.0,
          "conditions_passed": 0,
          "total_conditions": 0
        },
        {
          "name": "contrarian_watch_oversold",
          "status": "Idle",
          "score": 0.0,
          "conditions_passed": 0,
          "total_conditions": 0
        },
        {
          "name": "hilbert_cycle",
          "status": "Idle",
          "score": 0.0,
          "conditions_passed": 0,
          "total_conditions": 0
        },
        {
          "name": "stochastic_breakout",
          "status": "Idle",
          "score": 0.0,
          "conditions_passed": 0,
          "total_conditions": 0
        },
        {
          "name": "rsi_trend",
          "status": "Idle",
          "score": 0.0,
          "conditions_passed": 0,
          "total_conditions": 0
        },
        {
          "name": "bb_mean_reversion",
          "status": "Idle",
          "score": 0.0,
          "conditions_passed": 0,
          "total_conditions": 0
        },
        {
          "name": "ema_cross_fast",
          "status": "Idle",
          "score": 0.0,
          "conditions_passed": 0,
          "total_conditions": 0
        },
        {
          "name": "rsi_mid_bounce",
          "status": "Idle",
          "score": 0.0,
          "conditions_passed": 0,
          "total_conditions": 0
        },
        {
          "name": "volume_spike",
          "status": "Idle",
          "score": 0.0,
          "conditions_passed": 0,
          "total_conditions": 0
        },
        {
          "name": "price_channel_break",
          "status": "Idle",
          "score": 0.0,
          "conditions_passed": 0,
          "total_conditions": 0
        },
        {
          "name": "momentum_divergence",
          "status": "Idle",
          "score": 0.0,
          "conditions_passed": 0,
          "total_conditions": 0
        }
      ]
    },
    "AVAXUSDT": {
      "price": 9.11,
      "strategies": [
        {
          "name": "contrarian_watch_oversold",
          "status": "Watch",
          "score": 0.5,
          "conditions_passed": 2,
          "total_conditions": 2
        },
        {
          "name": "ma_cross_trend",
          "status": "Idle",
          "score": 0.0,
          "conditions_passed": 0,
          "total_conditions": 0
        },
        {
          "name": "ma_cross_trend_short",
          "status": "Idle",
          "score": 0.0,
          "conditions_passed": 0,
          "total_conditions": 0
        },
        {
          "name": "contrarian_watch_overheated",
          "status": "Idle",
          "score": 0.0,
          "conditions_passed": 0,
          "total_conditions": 0
        },
        {
          "name": "hilbert_cycle",
          "status": "Idle",
          "score": 0.0,
          "conditions_passed": 0,
          "total_conditions": 0
        },
        {
          "name": "stochastic_breakout",
          "status": "Idle",
          "score": 0.0,
          "conditions_passed": 0,
          "total_conditions": 0
        },
        {
          "name": "rsi_trend",
          "status": "Idle",
          "score": 0.0,
          "conditions_passed": 0,
          "total_conditions": 0
        },
        {
          "name": "bb_mean_reversion",
          "status": "Idle",
          "score": 0.0,
          "conditions_passed": 0,
          "total_conditions": 0
        },
        {
          "name": "ema_cross_fast",
          "status": "Idle",
          "score": 0.0,
          "conditions_passed": 0,
          "total_conditions": 0
        },
        {
          "name": "rsi_mid_bounce",
          "status": "Idle",
          "score": 0.0,
          "conditions_passed": 0,
          "total_conditions": 0
        },
        {
          "name": "volume_spike",
          "status": "Idle",
          "score": 0.0,
          "conditions_passed": 0,
          "total_conditions": 0
        },
        {
          "name": "price_channel_break",
          "status": "Idle",
          "score": 0.0,
          "conditions_passed": 0,
          "total_conditions": 0
        },
        {
          "name": "momentum_divergence",
          "status": "Idle",
          "score": 0.0,
          "conditions_passed": 0,
          "total_conditions": 0
        }
      ]
    },
    "LINKUSDT": {
      "price": 9.11,
      "strategies": [
        {
          "name": "ma_cross_trend",
          "status": "Idle",
          "score": 0.0,
          "conditions_passed": 0,
          "total_conditions": 0
        },
        {
          "name": "ma_cross_trend_short",
          "status": "Idle",
          "score": 0.0,
          "conditions_passed": 0,
          "total_conditions": 0
        },
        {
          "name": "contrarian_watch_overheated",
          "status": "Idle",
          "score": 0.0,
          "conditions_passed": 0,
          "total_conditions": 0
        },
        {
          "name": "contrarian_watch_oversold",
          "status": "Idle",
          "score": 0.0,
          "conditions_passed": 0,
          "total_conditions": 0
        },
        {
          "name": "hilbert_cycle",
          "status": "Idle",
          "score": 0.0,
          "conditions_passed": 0,
          "total_conditions": 0
        },
        {
          "name": "stochastic_breakout",
          "status": "Idle",
          "score": 0.0,
          "conditions_passed": 0,
          "total_conditions": 0
        },
        {
          "name": "rsi_trend",
          "status": "Idle",
          "score": 0.0,
          "conditions_passed": 0,
          "total_conditions": 0
        },
        {
          "name": "bb_mean_reversion",
          "status": "Idle",
          "score": 0.0,
          "conditions_passed": 0,
          "total_conditions": 0
        },
        {
          "name": "ema_cross_fast",
          "status": "Idle",
          "score": 0.0,
          "conditions_passed": 0,
          "total_conditions": 0
        },
        {
          "name": "rsi_mid_bounce",
          "status": "Idle",
          "score": 0.0,
          "conditions_passed": 0,
          "total_conditions": 0
        },
        {
          "name": "volume_spike",
          "status": "Idle",
          "score": 0.0,
          "conditions_passed": 0,
          "total_conditions": 0
        },
        {
          "name": "price_channel_break",
          "status": "Idle",
          "score": 0.0,
          "conditions_passed": 0,
          "total_conditions": 0
        },
        {
          "name": "momentum_divergence",
          "status": "Idle",
          "score": 0.0,
          "conditions_passed": 0,
          "total_conditions": 0
        }
      ]
    },
    "DOTUSDT": {
      "price": 1.206,
      "strategies": [
        {
          "name": "ma_cross_trend",
          "status": "Idle",
          "score": 0.0,
          "conditions_passed": 0,
          "total_conditions": 0
        },
        {
          "name": "ma_cross_trend_short",
          "status": "Idle",
          "score": 0.0,
          "conditions_passed": 0,
          "total_conditions": 0
        },
        {
          "name": "contrarian_watch_overheated",
          "status": "Idle",
          "score": 0.0,
          "conditions_passed": 0,
          "total_conditions": 0
        },
        {
          "name": "contrarian_watch_oversold",
          "status": "Idle",
          "score": 0.0,
          "conditions_passed": 0,
          "total_conditions": 0
        },
        {
          "name": "hilbert_cycle",
          "status": "Idle",
          "score": 0.0,
          "conditions_passed": 0,
          "total_conditions": 0
        },
        {
          "name": "stochastic_breakout",
          "status": "Idle",
          "score": 0.0,
          "conditions_passed": 0,
          "total_conditions": 0
        },
        {
          "name": "rsi_trend",
          "status": "Idle",
          "score": 0.0,
          "conditions_passed": 0,
          "total_conditions": 0
        },
        {
          "name": "bb_mean_reversion",
          "status": "Idle",
          "score": 0.0,
          "conditions_passed": 0,
          "total_conditions": 0
        },
        {
          "name": "ema_cross_fast",
          "status": "Idle",
          "score": 0.0,
          "conditions_passed": 0,
          "total_conditions": 0
        },
        {
          "name": "rsi_mid_bounce",
          "status": "Idle",
          "score": 0.0,
          "conditions_passed": 0,
          "total_conditions": 0
        },
        {
          "name": "volume_spike",
          "status": "Idle",
          "score": 0.0,
          "conditions_passed": 0,
          "total_conditions": 0
        },
        {
          "name": "price_channel_break",
          "status": "Idle",
          "score": 0.0,
          "conditions_passed": 0,
          "total_conditions": 0
        },
        {
          "name": "momentum_divergence",
          "status": "Idle",
          "score": 0.0,
          "conditions_passed": 0,
          "total_conditions": 0
        }
      ]
    }
  }
}